README.rst
setup.cfg
setup.py
rig/__init__.py
rig/bitfield.py
rig/geometry.py
rig/links.py
rig/machine.py
rig/netlist.py
rig/type_casts.py
rig/version.py
rig/wizard.py
rig.egg-info/PKG-INFO
rig.egg-info/SOURCES.txt
rig.egg-info/dependency_links.txt
rig.egg-info/entry_points.txt
rig.egg-info/requires.txt
rig.egg-info/top_level.txt
rig/binaries/test.aplx
rig/boot/sark.struct
rig/boot/scamp.boot
rig/machine_control/__init__.py
rig/machine_control/bmp_controller.py
rig/machine_control/boot.py
rig/machine_control/common.py
rig/machine_control/consts.py
rig/machine_control/machine_controller.py
rig/machine_control/packets.py
rig/machine_control/regions.py
rig/machine_control/scp_connection.py
rig/machine_control/struct_file.py
rig/machine_control/unbooted_ping.py
rig/machine_control/utils.py
rig/place_and_route/__init__.py
rig/place_and_route/constraints.py
rig/place_and_route/exceptions.py
rig/place_and_route/machine.py
rig/place_and_route/routing_tree.py
rig/place_and_route/utils.py
rig/place_and_route/wrapper.py
rig/place_and_route/allocate/__init__.py
rig/place_and_route/allocate/greedy.py
rig/place_and_route/allocate/utils.py
rig/place_and_route/place/__init__.py
rig/place_and_route/place/breadth_first.py
rig/place_and_route/place/hilbert.py
rig/place_and_route/place/rand.py
rig/place_and_route/place/rcm.py
rig/place_and_route/place/sequential.py
rig/place_and_route/place/utils.py
rig/place_and_route/place/sa/__init__.py
rig/place_and_route/place/sa/algorithm.py
rig/place_and_route/place/sa/c_kernel.py
rig/place_and_route/place/sa/kernel.py
rig/place_and_route/place/sa/python_kernel.py
rig/place_and_route/route/__init__.py
rig/place_and_route/route/ner.py
rig/place_and_route/route/utils.py
rig/routing_table/__init__.py
rig/routing_table/entries.py
rig/routing_table/exceptions.py
rig/routing_table/minimise.py
rig/routing_table/ordered_covering.py
rig/routing_table/remove_default_routes.py
rig/routing_table/utils.py
rig/scripts/__init__.py
rig/scripts/rig_boot.py
rig/scripts/rig_counters.py
rig/scripts/rig_discover.py
rig/scripts/rig_info.py
rig/scripts/rig_iobuf.py
rig/scripts/rig_power.py
rig/scripts/rig_ps.py
