Metadata-Version: 1.1
Name: rig
Version: 2.4.1
Summary: A collection of tools for developing SpiNNaker applications
Home-page: https://github.com/project-rig/rig
Author: The Rig Authors
Author-email: UNKNOWN
License: GPLv2
Keywords: spinnaker placement routing graph fixed-point
Platform: UNKNOWN
Classifier: Intended Audience :: Developers
Classifier: Intended Audience :: Science/Research
Classifier: License :: OSI Approved :: GNU General Public License v2 (GPLv2)
Classifier: Operating System :: POSIX :: Linux
Classifier: Operating System :: Microsoft :: Windows
Classifier: Operating System :: MacOS
Classifier: Programming Language :: Python :: 2
Classifier: Programming Language :: Python :: 2.7
Classifier: Programming Language :: Python :: 3
Classifier: Programming Language :: Python :: 3.4
Classifier: Programming Language :: Python :: 3.5
Classifier: Topic :: Software Development :: Libraries
